{
  "$schema": "https://biomejs.dev/schemas/2.0.4/schema.json",
  "vcs": {
    "enabled": true,
    "clientKind": "git",
    "useIgnoreFile": true
  },
  "files": {
    "ignoreUnknown": false
  },
  "formatter": {
    "enabled": true,
    "formatWithErrors": false,
    "indentStyle": "space",
    "indentWidth": 2,
    "lineEnding": "lf",
    "lineWidth": 80
  },
  "linter": {
    "enabled": true
  },
  "javascript": {
    "formatter": {
      "jsxQuoteStyle": "double",
      "quoteProperties": "asNeeded",
      "trailingCommas": "es5",
      "semicolons": "always",
      "arrowParentheses": "always",
      "bracketSpacing": true,
      "bracketSameLine": false,
      "quoteStyle": "single"
    }
  },
  "json": {
    "formatter": {
      "trailingCommas": "none"
    }
  }
}
